Metadata-Version: 2.1
Name: python-cryptobox
Version: 0.1.1
Summary: A cffi wrapper for cryptobox-c
Home-page: https://github.com/derEisele/python-cryptobox
Author: Alexander Eisele
Author-email: alexander@eiselecloud.de
License: GPLv3
Platform: UNKNOWN
Classifier: License :: OSI Approved :: GNU General Public License v3 (GPLv3)
Classifier: Programming Language :: Python
Classifier: Programming Language :: Python :: 3
Classifier: Programming Language :: Python :: 3.6
Classifier: Programming Language :: Python :: Implementation :: CPython
Classifier: Programming Language :: Python :: Implementation :: PyPy
Classifier: Operating System :: POSIX :: Linux
Requires-Python: >=3.6.0
